MANIFEST.in
README.rst
setup.py
django_dynamic_sprites.egg-info/PKG-INFO
django_dynamic_sprites.egg-info/SOURCES.txt
django_dynamic_sprites.egg-info/dependency_links.txt
django_dynamic_sprites.egg-info/requires.txt
django_dynamic_sprites.egg-info/top_level.txt
dynamic_sprites/__init__.py
dynamic_sprites/conf.py
dynamic_sprites/image.py
dynamic_sprites/listeners.py
dynamic_sprites/model_sprite.py
dynamic_sprites/output_css.py
dynamic_sprites/packing.py
dynamic_sprites/slugify.py
dynamic_sprites/sprite.py
dynamic_sprites/utils.py
scripts/__init__.py
scripts/generate_sprite.py
tests/tests/__init__.py
tests/tests/helpers.py
tests/tests/test_bin_packing.py
tests/tests/test_image.py
tests/tests/test_linear_packing.py
tests/tests/test_listener.py
tests/tests/test_script.py
tests/tests/test_sprite.py
tests/tests/test_sprite_for_model.py