Metadata-Version: 1.0
Name: django-dynamic-sprites
Version: 0.1.3
Summary: A way to generate sprites based on objects created by the application user.
Home-page: https://github.com/vbmendes/django-dynamic-sprites
Author: Vinicius Mendes
Author-email: vbmendes@gmail.com
License: BSD
Download-URL: https://github.com/vbmendes/django-dynamic-sprites/downloads
Platform: UNKNOWN
Classifier: Development Status :: 1 - Planning
Classifier: Environment :: Web Environment
Classifier: Framework :: Django
Classifier: Intended Audience :: Developers
Classifier: License :: OSI Approved :: BSD License
Classifier: Operating System :: OS Independent
Classifier: Programming Language :: Python
Classifier: Topic :: Software Development :: Libraries :: Python Modules
Classifier: Topic :: Multimedia :: Graphics :: Graphics Conversion
